nsfw_dl/__init__.py
nsfw_dl/__main__.py
nsfw_dl/bases.py
nsfw_dl/dl.py
nsfw_dl/errors.py
nsfw_dl/loaders/__init__.py
nsfw_dl/loaders/danbooru.py
nsfw_dl/loaders/drunkenpumken.py
nsfw_dl/loaders/e621.py
nsfw_dl/loaders/furrybooru.py
nsfw_dl/loaders/gelbooru.py
nsfw_dl/loaders/hbrowse.py
nsfw_dl/loaders/konachan.py
nsfw_dl/loaders/lolibooru.py
nsfw_dl/loaders/nhentai.py
nsfw_dl/loaders/rule34.py
nsfw_dl/loaders/tbib.py
nsfw_dl/loaders/tsumino.py
nsfw_dl/loaders/xbooru.py
nsfw_dl/loaders/yandere.py
nsfw_dl-0.4.1.dist-info/DESCRIPTION.rst
nsfw_dl-0.4.1.dist-info/METADATA
nsfw_dl-0.4.1.dist-info/RECORD
nsfw_dl-0.4.1.dist-info/WHEEL
nsfw_dl-0.4.1.dist-info/entry_points.txt
nsfw_dl-0.4.1.dist-info/metadata.json
nsfw_dl-0.4.1.dist-info/top_level.txt
