Metadata-Version: 2.0
Name: nsfw-dl
Version: 0.4.1
Summary: Python 3 package for downloading nsfw images.
Home-page: https://github.com/IzunaDevs/nsfw_dl
Author: IzunaDevs
Author-email: izunadevs@martmists.com
License: MIT
Download-URL: https://github.com/IzunaDevs/nsfw_dl
Platform: Any
Classifier: Development Status :: 4 - Beta
Classifier: Intended Audience :: Developers
Classifier: License :: OSI Approved :: MIT License
Classifier: Natural Language :: English
Classifier: Operating System :: OS Independent
Classifier: Programming Language :: Python :: 3.6
Classifier: Topic :: Software Development :: Libraries
Classifier: Topic :: Software Development :: Libraries :: Python Modules
Classifier: Topic :: Utilities
Requires-Dist: aiohttp (>=2.2.0)
Requires-Dist: beautifulsoup4 (>=4.6.0)
Requires-Dist: lxml (>=3.8.0)
